jinjanator/__init__.py
jinjanator/cli.py
jinjanator/context.py
jinjanator/customize.py
jinjanator/filters.py
jinjanator/formats.py
jinjanator/py.typed
jinjanator/version.py
jinjanator-25.3.0.dist-info/METADATA
jinjanator-25.3.0.dist-info/WHEEL
jinjanator-25.3.0.dist-info/entry_points.txt
jinjanator-25.3.0.dist-info/licenses/LICENSE.apache-2.0
jinjanator-25.3.0.dist-info/licenses/LICENSE.bsd-2-clause
jinjanator-25.3.0.dist-info/RECORD
