Metadata-Version: 2.3
Name: jinjanator
Version: 25.3.0
Summary: Command-line interface to Jinja2 for templating in shell scripts.
Project-URL: Bug Tracker, https://github.com/kpfleming/jinjanator/issues
Project-URL: Homepage, https://github.com/kpfleming/jinjanator
Author-email: "Kevin P. Fleming" <jinjanator@kevin.km6g.us>, Mark Vartanyan <kolypto@gmail.com>
License: Apache-2.0
Classifier: Development Status :: 5 - Production/Stable
Classifier: Environment :: Console
Classifier: Intended Audience :: Developers
Classifier: Intended Audience :: System Administrators
Classifier: Natural Language :: English
Classifier: Operating System :: OS Independent
Classifier: Programming Language :: Python :: 3 :: Only
Classifier: Programming Language :: Python :: 3.10
Classifier: Programming Language :: Python :: 3.11
Classifier: Programming Language :: Python :: 3.12
Classifier: Programming Language :: Python :: 3.13
Classifier: Programming Language :: Python :: 3.14
Classifier: Typing :: Typed
Requires-Python: >=3.10
Requires-Dist: attrs
Requires-Dist: jinja2>=2.7.2
Requires-Dist: jinjanator-plugins==25.1.*
Requires-Dist: python-dotenv>=1
Requires-Dist: pyyaml
Requires-Dist: typing-extensions
